screen.py
screenreclib-0.1.dist-info/licenses/LICENSE
screenreclib-0.1.dist-info/METADATA
screenreclib-0.1.dist-info/WHEEL
screenreclib-0.1.dist-info/top_level.txt
screenreclib-0.1.dist-info/RECORD
