Metadata-Version: 2.4
Name: screenreclib
Version: 0.1
Home-page: https://github.com/SotiralKeepsGettingHacked/screenreclib
Classifier: Programming Language :: Python :: 3
Classifier: License :: OSI Approved :: MIT License
Classifier: Operating System :: OS Independent
License-File: LICENSE
Dynamic: classifier
Dynamic: description
Dynamic: description-content-type
Dynamic: home-page
Dynamic: license-file
